velo_sdk/__init__.py
velo_sdk/api/__init__.py
velo_sdk/api/api_client.py
velo_sdk/api/assets.py
velo_sdk/api/base.py
velo_sdk/api/climate.py
velo_sdk/api/companies.py
velo_sdk/api/errors.py
velo_sdk/api/markets.py
velo_sdk/api/pagination.py
velo_sdk/api/static_list.py
velo_sdk/api/types.py
velo_sdk-0.0.16.dist-info/licenses/LICENSE
velo_sdk-0.0.16.dist-info/METADATA
velo_sdk-0.0.16.dist-info/WHEEL
velo_sdk-0.0.16.dist-info/top_level.txt
velo_sdk-0.0.16.dist-info/RECORD
