Metadata-Version: 2.4
Name: velo-sdk
Version: 0.0.16
Summary: Python SDK for accessing the VELO API for climate risk data, asset information, companies, and market indexes
Author-email: Chris Hampu <champu@riskthinking.ai>, "RiskThinking.AI" <velo@riskthinking.ai>
License-Expression: Apache-2.0
Project-URL: Homepage, https://riskthinking.ai
Project-URL: Documentation, https://api.docs.riskthinking.ai
Project-URL: Source, https://github.com/RiskThinking/velo-sdk
Project-URL: Bug Tracker, https://github.com/RiskThinking/velo-sdk/issues
Keywords: climate,risk,finance,assets,api
Classifier: Development Status :: 5 - Production/Stable
Classifier: Intended Audience :: Financial and Insurance Industry
Classifier: Programming Language :: Python :: 3
Classifier: Programming Language :: Python :: 3.11
Classifier: Topic :: Office/Business :: Financial
Classifier: Topic :: Scientific/Engineering :: Information Analysis
Requires-Python: >=3.11
License-File: LICENSE
Requires-Dist: httpx>=0.28.1
Requires-Dist: pydantic>=2.10.6
Requires-Dist: polars>=1.20
Requires-Dist: backoff>=2.2.1
Dynamic: license-file
